edgetest_conda/__init__.py
edgetest_conda/plugin.py
edgetest_conda-2024.4.0.dist-info/AUTHORS.md
edgetest_conda-2024.4.0.dist-info/LICENSE
edgetest_conda-2024.4.0.dist-info/METADATA
edgetest_conda-2024.4.0.dist-info/WHEEL
edgetest_conda-2024.4.0.dist-info/entry_points.txt
edgetest_conda-2024.4.0.dist-info/top_level.txt
edgetest_conda-2024.4.0.dist-info/RECORD
