Metadata-Version: 2.1
Name: edgetest-conda
Version: 2024.4.0
Summary: Conda edgetest plugin
Home-page: https://github.com/capitalone/edgetest-conda
Author: Akshay Gupta
Author-email: akshay.gupta2@capitalone.com
Maintainer: Akshay Gupta
Maintainer-email: akshay.gupta2@capitalone.com
Project-URL: Documentation, https://capitalone.github.io/edgetest-conda
Project-URL: Bug Tracker, https://github.com/capitalone/edgetest-conda/issues
Project-URL: Source Code, https://github.com/capitalone/edgetest-conda
Classifier: Intended Audience :: Developers
Classifier: Natural Language :: English
Classifier: Operating System :: OS Independent
Classifier: Programming Language :: Python
Classifier: Programming Language :: Python :: 3
Classifier: Programming Language :: Python :: 3 :: Only
Classifier: Programming Language :: Python :: 3.8
Classifier: Programming Language :: Python :: 3.9
Classifier: Programming Language :: Python :: 3.10
Classifier: Programming Language :: Python :: 3.11
License-File: LICENSE
License-File: AUTHORS.md
Requires-Dist: edgetest >=2022.3.0
Provides-Extra: build
Requires-Dist: build ; extra == 'build'
Requires-Dist: twine ; extra == 'build'
Requires-Dist: wheel ; extra == 'build'
Requires-Dist: bumpver ; extra == 'build'
Provides-Extra: dev
Requires-Dist: coverage ; extra == 'dev'
Requires-Dist: flake8 ; extra == 'dev'
Requires-Dist: mypy ; extra == 'dev'
Requires-Dist: pydocstyle ; extra == 'dev'
Requires-Dist: pytest ; extra == 'dev'
Requires-Dist: pytest-cov ; extra == 'dev'
Requires-Dist: furo ; extra == 'dev'
Requires-Dist: sphinx ; extra == 'dev'
Requires-Dist: sphinx-copybutton ; extra == 'dev'
Requires-Dist: sphinx-tabs ; extra == 'dev'
Requires-Dist: black ; extra == 'dev'
Requires-Dist: isort ; extra == 'dev'
Requires-Dist: pip-tools ; extra == 'dev'
Requires-Dist: pre-commit ; extra == 'dev'
Requires-Dist: pylint ; extra == 'dev'
Requires-Dist: build ; extra == 'dev'
Requires-Dist: twine ; extra == 'dev'
Requires-Dist: wheel ; extra == 'dev'
Requires-Dist: bumpver ; extra == 'dev'
Provides-Extra: docs
Requires-Dist: furo ; extra == 'docs'
Requires-Dist: sphinx ; extra == 'docs'
Requires-Dist: sphinx-copybutton ; extra == 'docs'
Requires-Dist: sphinx-tabs ; extra == 'docs'
Provides-Extra: qa
Requires-Dist: black ; extra == 'qa'
Requires-Dist: isort ; extra == 'qa'
Requires-Dist: pip-tools ; extra == 'qa'
Requires-Dist: pre-commit ; extra == 'qa'
Requires-Dist: pylint ; extra == 'qa'
Provides-Extra: tests
Requires-Dist: coverage ; extra == 'tests'
Requires-Dist: flake8 ; extra == 'tests'
Requires-Dist: mypy ; extra == 'tests'
Requires-Dist: pydocstyle ; extra == 'tests'
Requires-Dist: pytest ; extra == 'tests'
Requires-Dist: pytest-cov ; extra == 'tests'
